CTkCalendar/__init__.py
CTkCalendar/ctkcalendar.py
CTKCalendar-0.0.1.dist-info/LICENSE
CTKCalendar-0.0.1.dist-info/METADATA
CTKCalendar-0.0.1.dist-info/WHEEL
CTKCalendar-0.0.1.dist-info/top_level.txt
CTKCalendar-0.0.1.dist-info/RECORD
